{
  "db_name": "PostgreSQL",
  "query": "SELECT * FROM downloads",
  "describe": {
    "columns": [
      {
        "ordinal": 0,
        "name": "id",
        "type_info": "Int8"
      },
      {
        "ordinal": 1,
        "name": "url",
        "type_info": "Text"
      },
      {
        "ordinal": 2,
        "name": "status",
        "type_info": "Text"
      },
      {
        "ordinal": 3,
        "name": "created_at",
        "type_info": "Timestamptz"
      },
      {
        "ordinal": 4,
        "name": "updated_at",
        "type_info": "Timestamptz"
      },
      {
        "ordinal": 5,
        "name": "completed_at",
        "type_info": "Timestamptz"
      }
    ],
    "parameters": {
      "Left": []
    },
    "nullable": [
      false,
      false,
      false,
      false,
      false,
      true
    ]
  },
  "hash": "c63ef6bbc5297fce12433a0ed3f0f7b481eb4036e987afd633b7fdbadd8c8ffd"
}
